gpt_commit/__init__.py
gpt_commit/cli.py
gpt_commit/utils.py
gpt_commit_cli-0.1.1.dist-info/entry_points.txt
gpt_commit_cli-0.1.1.dist-info/LICENSE
gpt_commit_cli-0.1.1.dist-info/LICENSE.Markus
gpt_commit_cli-0.1.1.dist-info/WHEEL
gpt_commit_cli-0.1.1.dist-info/METADATA
gpt_commit_cli-0.1.1.dist-info/RECORD
