Metadata-Version: 2.1
Name: gpt-commit-cli
Version: 0.1.1
Summary: Generate commit messages using GPT-3.
Home-page: https://github.com/tddschn/gpt-commit-cli
License: MIT
Keywords: GPT-3,Git commit,Git,cli
Author: Teddy Xinyuan Chen
Author-email: 45612704+tddschn@users.noreply.github.com
Requires-Python: >=3.10,<4.0
Classifier: License :: OSI Approved :: MIT License
Classifier: Programming Language :: Python :: 3
Classifier: Programming Language :: Python :: 3.10
Classifier: Topic :: Utilities
Requires-Dist: openai (>=0.26.5,<0.27.0)
Project-URL: Bug Tracker, https://github.com/tddschn/gpt-commit-cli/issues
Project-URL: Repository, https://github.com/tddschn/gpt-commit-cli
